pycpfcnpj/__init__.py
pycpfcnpj/calculation.py
pycpfcnpj/cnpj.py
pycpfcnpj/compatible.py
pycpfcnpj/cpf.py
pycpfcnpj/cpfcnpj.py
pycpfcnpj/gen.py
pycpfcnpj-1.9.dist-info/WHEEL
pycpfcnpj-1.9.dist-info/METADATA
pycpfcnpj-1.9.dist-info/RECORD
