Metadata-Version: 2.4
Name: pycpfcnpj
Version: 1.9
Summary: Python module for brazilian register numbers for persons (CPF) and companies (CNPJ).
Author: Matheus CAS
Author-email: Matheus CAS <matheus.mcas@gmail.com>
License-Expression: MIT
Classifier: Programming Language :: Python :: 3
Classifier: Programming Language :: Python :: 3.8
Classifier: Programming Language :: Python :: 3.9
Classifier: Programming Language :: Python :: 3.10
Classifier: Programming Language :: Python :: 3.11
Classifier: Programming Language :: Python :: 3.12
Classifier: Programming Language :: Python :: 3.13
Classifier: Programming Language :: Python :: 3.14
Requires-Python: >=3.8, <4
